guillotina_prometheus/__init__.py
guillotina_prometheus/api.py
guillotina_prometheus/metrics.py
guillotina_prometheus/middleware.py
guillotina_prometheus-6.0.0.dist-info/LICENSE
guillotina_prometheus-6.0.0.dist-info/METADATA
guillotina_prometheus-6.0.0.dist-info/WHEEL
guillotina_prometheus-6.0.0.dist-info/top_level.txt
guillotina_prometheus-6.0.0.dist-info/RECORD
