Metadata-Version: 2.1
Name: guillotina-prometheus
Version: 6.0.0
Summary: prometheus integration into guillotina
Home-page: https://github.com/guillotinaweb/guillotina_prometheus
Author: Nathan Van Gheem
Author-email: vangheem@gmail.com
License: BSD
Platform: UNKNOWN
Classifier: License :: OSI Approved :: BSD License
Classifier: Intended Audience :: Developers
Classifier: Topic :: Internet :: WWW/HTTP
Classifier: Programming Language :: Python :: 3.6
Classifier: Topic :: Software Development :: Libraries :: Python Modules
Requires-Dist: guillotina (>=6.0.0a6)
Requires-Dist: prometheus-client (==0.7.1)
Provides-Extra: test
Requires-Dist: pytest ; extra == 'test'
